KalturaClient/Base.py
KalturaClient/__init__.py
KalturaClient/Client.py
KalturaClient/exceptions.py
KalturaClient/Plugins/__init__.py
KalturaClient/Plugins/Core.py
KalturaOttApiClient-5.0.2.25914.dist-info/metadata.json
KalturaOttApiClient-5.0.2.25914.dist-info/RECORD
KalturaOttApiClient-5.0.2.25914.dist-info/WHEEL
KalturaOttApiClient-5.0.2.25914.dist-info/DESCRIPTION.rst
KalturaOttApiClient-5.0.2.25914.dist-info/METADATA
KalturaOttApiClient-5.0.2.25914.dist-info/top_level.txt
