Metadata-Version: 2.0
Name: KalturaOttApiClient
Version: 5.0.2.25914
Summary: A Python module for accessing the Kaltura OTT API.
Home-page: https://github.com/kaltura/KalturaOttGeneratedAPIClientsPython
Author: UNKNOWN
Author-email: UNKNOWN
License: AGPLv3+
Keywords: Kaltura OTT API client
Platform: UNKNOWN
Classifier: Development Status :: 5 - Production/Stable
Classifier: Intended Audience :: Developers
Classifier: Topic :: Software Development :: Build Tools
Classifier: License :: OSI Approved :: GNU Affero General Public License v3 or later (AGPLv3+)
Classifier: Programming Language :: Python :: 2.7
Classifier: Programming Language :: Python :: 3
Classifier: Programming Language :: Python :: 3.3
Classifier: Programming Language :: Python :: 3.4
Classifier: Programming Language :: Python :: 3.5
Requires-Dist: requests (>=2.4.2)
Requires-Dist: requests-toolbelt
Requires-Dist: six
